mixed.py
setup.py
mixed.egg-info/PKG-INFO
mixed.egg-info/SOURCES.txt
mixed.egg-info/dependency_links.txt
mixed.egg-info/top_level.txt
