Metadata-Version: 1.0
Name: mixed
Version: 0.2.1
Summary: Class for fractions and mixed numbers
Home-page: http://trac-hg.assembla.com/mixed_python/
Author: Catherine Devlin
Author-email: catherine.devlin@gmail.com
License: MIT
Keywords: fraction arithmetic
Platform: UNKNOWN
Classifier: Development Status :: 3 - Alpha
Classifier: Operating System :: OS Independent
Classifier: Programming Language :: Python
Classifier: License :: OSI Approved :: MIT License
Classifier: Topic :: Software Development :: Libraries :: Python Modules
Classifier: Topic :: Scientific/Engineering :: Mathematics
